idustorage/__init__.py
idustorage/_version.py
idustorage/storage/__init__.py
idustorage/storage/interfaces/__init__.py
idustorage/storage/interfaces/cacheable.py
idustorage/storage/interfaces/storage_interface.py
idustorage/storage/storage.py
idustorage-1.1.4.dist-info/METADATA
idustorage-1.1.4.dist-info/WHEEL
idustorage-1.1.4.dist-info/RECORD
